<?xml version="1.0" encoding="ISO-8859-1"?>
<attributes>
<attribute>
<srcPos sline="0" eline="0" spos="0" epos="0"/>
<jmpPos sline="0" eline="0" spos="0" epos="0"/>
<text info="[inner=javassist/bytecode/AnnotationsAttribute$Copier, outer=javassist/bytecode/AnnotationsAttribute, name=Copier,flags=8]" aType="InnerClassTag"/>
<text info="[inner=javassist/bytecode/AnnotationsAttribute$Parser, outer=javassist/bytecode/AnnotationsAttribute, name=Parser,flags=8]" aType="InnerClassTag"/>
<text info="soot.tagkit.InnerClassAttribute@17bf72d3" aType="InnerClassAttribute"/>
</attribute>
<attribute>
<srcPos sline="0" eline="0" spos="0" epos="0"/>
<jmpPos sline="3" eline="3" spos="0" epos="0"/>
<text info="ConstantValue: AnnotationDefault" aType="StringConstantValueTag"/>
</attribute>
<attribute>
<srcPos sline="0" eline="0" spos="0" epos="0"/>
<jmpPos sline="63" eline="63" spos="0" epos="0"/>
<text info="Signature: (Ljavassist/bytecode/ConstPool;Ljava/util/Map<Ljava/lang/String;Ljava/lang/String;>;)Ljavassist/bytecode/AttributeInfo;" aType="SignatureTag"/>
</attribute>
</attributes>
