<?xml version="1.0" encoding="ISO-8859-1"?>
<attributes>
<attribute>
<srcPos sline="0" eline="0" spos="0" epos="0"/>
<jmpPos sline="3" eline="3" spos="0" epos="0"/>
<text info="ConstantValue: 7284183123441947635" aType="LongConstantValueTag"/>
</attribute>
<attribute>
<srcPos sline="0" eline="0" spos="0" epos="0"/>
<jmpPos sline="7" eline="7" spos="0" epos="0"/>
<text info="Signature: Ljava/lang/ref/WeakReference<Ljava/lang/Throwable;>;" aType="SignatureTag"/>
</attribute>
<attribute>
<srcPos sline="0" eline="0" spos="0" epos="0"/>
<jmpPos sline="28" eline="28" spos="0" epos="0"/>
<text info="Signature: (Ljava/lang/Throwable;Ljava/util/Set<Ljava/lang/Throwable;>;)V" aType="SignatureTag"/>
</attribute>
</attributes>
