<?xml version="1.0" encoding="ISO-8859-1"?>
<attributes>
<attribute>
<srcPos sline="0" eline="0" spos="0" epos="0"/>
<jmpPos sline="0" eline="0" spos="0" epos="0"/>
<text info="Signature: <E:Ljava/lang/Object;>Lorg/apache/flink/shaded/guava18/com/google/common/collect/Synchronized$SynchronizedCollection<TE;>;Ljava/util/Queue<TE;>;" aType="SignatureTag"/>
<text info="[inner=org/apache/flink/shaded/guava18/com/google/common/collect/Synchronized$SynchronizedQueue, outer=org/apache/flink/shaded/guava18/com/google/common/collect/Synchronized, name=SynchronizedQueue,flags=10]" aType="InnerClassTag"/>
<text info="[inner=org/apache/flink/shaded/guava18/com/google/common/collect/Synchronized$SynchronizedCollection, outer=org/apache/flink/shaded/guava18/com/google/common/collect/Synchronized, name=SynchronizedCollection,flags=8]" aType="InnerClassTag"/>
<text info="[inner=org/apache/flink/shaded/guava18/com/google/common/collect/Synchronized$1, outer=org/apache/flink/shaded/guava18/com/google/common/collect/Synchronized, name=null,flags=4104]" aType="InnerClassTag"/>
<text info="soot.tagkit.InnerClassAttribute@2a103a92" aType="InnerClassAttribute"/>
</attribute>
<attribute>
<srcPos sline="0" eline="0" spos="0" epos="0"/>
<jmpPos sline="3" eline="3" spos="0" epos="0"/>
<text info="ConstantValue: 0" aType="LongConstantValueTag"/>
</attribute>
<attribute>
<srcPos sline="0" eline="0" spos="0" epos="0"/>
<jmpPos sline="5" eline="5" spos="0" epos="0"/>
<text info="Signature: (Ljava/util/Queue<TE;>;Ljava/lang/Object;)V" aType="SignatureTag"/>
<text info="Visibility Param Annotation: num params: 2 kind: 0

Visibility Annotation: level: RUNTIME (runtime-visible)
 Annotations:
Annotation type: Ljavax/annotation/Nullable; without elements

" aType="VisibilityParameterAnnotationTag"/>
</attribute>
<attribute>
<srcPos sline="0" eline="0" spos="0" epos="0"/>
<jmpPos sline="22" eline="22" spos="0" epos="0"/>
<text info="Signature: ()Ljava/util/Queue<TE;>;" aType="SignatureTag"/>
</attribute>
<attribute>
<srcPos sline="0" eline="0" spos="0" epos="0"/>
<jmpPos sline="37" eline="37" spos="0" epos="0"/>
<text info="Signature: ()TE;" aType="SignatureTag"/>
</attribute>
<attribute>
<srcPos sline="0" eline="0" spos="0" epos="0"/>
<jmpPos sline="72" eline="72" spos="0" epos="0"/>
<text info="Signature: (TE;)Z" aType="SignatureTag"/>
</attribute>
<attribute>
<srcPos sline="0" eline="0" spos="0" epos="0"/>
<jmpPos sline="110" eline="110" spos="0" epos="0"/>
<text info="Signature: ()TE;" aType="SignatureTag"/>
</attribute>
<attribute>
<srcPos sline="0" eline="0" spos="0" epos="0"/>
<jmpPos sline="145" eline="145" spos="0" epos="0"/>
<text info="Signature: ()TE;" aType="SignatureTag"/>
</attribute>
<attribute>
<srcPos sline="0" eline="0" spos="0" epos="0"/>
<jmpPos sline="180" eline="180" spos="0" epos="0"/>
<text info="Signature: ()TE;" aType="SignatureTag"/>
</attribute>
</attributes>
