<?xml version="1.0" encoding="ISO-8859-1"?>
<attributes>
<attribute>
<srcPos sline="0" eline="0" spos="0" epos="0"/>
<jmpPos sline="0" eline="0" spos="0" epos="0"/>
<text info="[inner=org/apache/flink/core/io/PostVersionedIOReadableWritableTest$TestByteArrayInputStreamProducingOneByteAtATime, outer=org/apache/flink/core/io/PostVersionedIOReadableWritableTest, name=TestByteArrayInputStreamProducingOneByteAtATime,flags=8]" aType="InnerClassTag"/>
<text info="[inner=org/apache/flink/core/io/PostVersionedIOReadableWritableTest$TestNonVersionedReadableWritable, outer=org/apache/flink/core/io/PostVersionedIOReadableWritableTest, name=TestNonVersionedReadableWritable,flags=8]" aType="InnerClassTag"/>
<text info="[inner=org/apache/flink/core/io/PostVersionedIOReadableWritableTest$TestPostVersionedReadableWritable, outer=org/apache/flink/core/io/PostVersionedIOReadableWritableTest, name=TestPostVersionedReadableWritable,flags=8]" aType="InnerClassTag"/>
<text info="soot.tagkit.InnerClassAttribute@58abca0" aType="InnerClassAttribute"/>
</attribute>
<attribute>
<srcPos sline="0" eline="0" spos="0" epos="0"/>
<jmpPos sline="15" eline="15" spos="0" epos="0"/>
<text info="Visibility Annotation: level: RUNTIME (runtime-visible)
 Annotations:
Annotation type: Lorg/junit/Test; without elements
" aType="VisibilityAnnotationTag"/>
</attribute>
<attribute>
<srcPos sline="0" eline="0" spos="0" epos="0"/>
<jmpPos sline="39" eline="39" spos="0" epos="0"/>
<text info="Visibility Annotation: level: RUNTIME (runtime-visible)
 Annotations:
Annotation type: Lorg/junit/Test; without elements
" aType="VisibilityAnnotationTag"/>
</attribute>
<attribute>
<srcPos sline="0" eline="0" spos="0" epos="0"/>
<jmpPos sline="68" eline="68" spos="0" epos="0"/>
<text info="Visibility Annotation: level: RUNTIME (runtime-visible)
 Annotations:
Annotation type: Lorg/junit/Test; without elements
" aType="VisibilityAnnotationTag"/>
</attribute>
<attribute>
<srcPos sline="0" eline="0" spos="0" epos="0"/>
<jmpPos sline="92" eline="92" spos="0" epos="0"/>
<text info="Visibility Annotation: level: RUNTIME (runtime-visible)
 Annotations:
Annotation type: Lorg/junit/Test; without elements
" aType="VisibilityAnnotationTag"/>
</attribute>
<attribute>
<srcPos sline="0" eline="0" spos="0" epos="0"/>
<jmpPos sline="117" eline="117" spos="0" epos="0"/>
<text info="Visibility Annotation: level: RUNTIME (runtime-visible)
 Annotations:
Annotation type: Lorg/junit/Test; without elements
" aType="VisibilityAnnotationTag"/>
</attribute>
</attributes>
