<?xml version="1.0" encoding="ISO-8859-1"?>
<attributes>
<attribute>
<srcPos sline="0" eline="0" spos="0" epos="0"/>
<jmpPos sline="0" eline="0" spos="0" epos="0"/>
<text info="Signature: Lorg/apache/flink/types/parser/ParserTestBase<Ljava/lang/Byte;>;" aType="SignatureTag"/>
</attribute>
<attribute>
<srcPos sline="0" eline="0" spos="0" epos="0"/>
<jmpPos sline="152" eline="152" spos="0" epos="0"/>
<text info="Signature: ()Lorg/apache/flink/types/parser/FieldParser<Ljava/lang/Byte;>;" aType="SignatureTag"/>
</attribute>
<attribute>
<srcPos sline="0" eline="0" spos="0" epos="0"/>
<jmpPos sline="166" eline="166" spos="0" epos="0"/>
<text info="Signature: ()Ljava/lang/Class<Ljava/lang/Byte;>;" aType="SignatureTag"/>
</attribute>
</attributes>
