<?xml version="1.0" encoding="ISO-8859-1"?>
<attributes>
<attribute>
<srcPos sline="0" eline="0" spos="0" epos="0"/>
<jmpPos sline="0" eline="0" spos="0" epos="0"/>
<text info="Signature: <T:Ljava/lang/Object;>Lorg/apache/flink/api/common/typeutils/CompositeTypeComparator<TT;>;Ljava/io/Serializable;" aType="SignatureTag"/>
<text info="Visibility Annotation: level: CLASS (runtime-invisible)
 Annotations:
Annotation type: Lorg/apache/flink/annotation/Internal; without elements
" aType="VisibilityAnnotationTag"/>
</attribute>
<attribute>
<srcPos sline="0" eline="0" spos="0" epos="0"/>
<jmpPos sline="3" eline="3" spos="0" epos="0"/>
<text info="ConstantValue: 1" aType="LongConstantValueTag"/>
</attribute>
<attribute>
<srcPos sline="0" eline="0" spos="0" epos="0"/>
<jmpPos sline="5" eline="5" spos="0" epos="0"/>
<text info="Signature: [Lorg/apache/flink/api/common/typeutils/TypeComparator<Ljava/lang/Object;>;" aType="SignatureTag"/>
</attribute>
<attribute>
<srcPos sline="0" eline="0" spos="0" epos="0"/>
<jmpPos sline="10" eline="10" spos="0" epos="0"/>
<text info="Signature: Lorg/apache/flink/api/common/typeutils/TypeSerializer<TT;>;" aType="SignatureTag"/>
</attribute>
<attribute>
<srcPos sline="0" eline="0" spos="0" epos="0"/>
<jmpPos sline="11" eline="11" spos="0" epos="0"/>
<text info="Signature: Ljava/lang/Class<TT;>;" aType="SignatureTag"/>
</attribute>
<attribute>
<srcPos sline="0" eline="0" spos="0" epos="0"/>
<jmpPos sline="13" eline="13" spos="0" epos="0"/>
<text info="Signature: ([Ljava/lang/reflect/Field;[Lorg/apache/flink/api/common/typeutils/TypeComparator<*>;Lorg/apache/flink/api/common/typeutils/TypeSerializer<TT;>;Ljava/lang/Class<TT;>;)V" aType="SignatureTag"/>
</attribute>
<attribute>
<srcPos sline="0" eline="0" spos="0" epos="0"/>
<jmpPos sline="193" eline="193" spos="0" epos="0"/>
<text info="Signature: (Lorg/apache/flink/api/java/typeutils/runtime/PojoComparator<TT;>;)V" aType="SignatureTag"/>
</attribute>
<attribute>
<srcPos sline="0" eline="0" spos="0" epos="0"/>
<jmpPos sline="399" eline="399" spos="0" epos="0"/>
<text info="Signature: (Ljava/util/List<Lorg/apache/flink/api/common/typeutils/TypeComparator;>;)V" aType="SignatureTag"/>
</attribute>
<attribute>
<srcPos sline="0" eline="0" spos="0" epos="0"/>
<jmpPos sline="533" eline="533" spos="0" epos="0"/>
<text info="Signature: (TT;)I" aType="SignatureTag"/>
</attribute>
<attribute>
<srcPos sline="0" eline="0" spos="0" epos="0"/>
<jmpPos sline="625" eline="625" spos="0" epos="0"/>
<text info="Signature: (TT;)V" aType="SignatureTag"/>
</attribute>
<attribute>
<srcPos sline="0" eline="0" spos="0" epos="0"/>
<jmpPos sline="668" eline="668" spos="0" epos="0"/>
<text info="Signature: (TT;)Z" aType="SignatureTag"/>
</attribute>
<attribute>
<srcPos sline="0" eline="0" spos="0" epos="0"/>
<jmpPos sline="717" eline="717" spos="0" epos="0"/>
<text info="Signature: (Lorg/apache/flink/api/common/typeutils/TypeComparator<TT;>;)I" aType="SignatureTag"/>
</attribute>
<attribute>
<srcPos sline="0" eline="0" spos="0" epos="0"/>
<jmpPos sline="786" eline="786" spos="0" epos="0"/>
<text info="Signature: (TT;TT;)I" aType="SignatureTag"/>
</attribute>
<attribute>
<srcPos sline="0" eline="0" spos="0" epos="0"/>
<jmpPos sline="951" eline="951" spos="0" epos="0"/>
<text info="Signature: (TT;Lorg/apache/flink/core/memory/MemorySegment;II)V" aType="SignatureTag"/>
</attribute>
<attribute>
<srcPos sline="0" eline="0" spos="0" epos="0"/>
<jmpPos sline="1041" eline="1041" spos="0" epos="0"/>
<text info="Signature: (TT;Lorg/apache/flink/core/memory/DataOutputView;)V" aType="SignatureTag"/>
</attribute>
<attribute>
<srcPos sline="0" eline="0" spos="0" epos="0"/>
<jmpPos sline="1061" eline="1061" spos="0" epos="0"/>
<text info="Signature: (TT;Lorg/apache/flink/core/memory/DataInputView;)TT;" aType="SignatureTag"/>
</attribute>
<attribute>
<srcPos sline="0" eline="0" spos="0" epos="0"/>
<jmpPos sline="1081" eline="1081" spos="0" epos="0"/>
<text info="Signature: ()Lorg/apache/flink/api/java/typeutils/runtime/PojoComparator<TT;>;" aType="SignatureTag"/>
</attribute>
</attributes>
