<?xml version="1.0" encoding="ISO-8859-1"?>
<attributes>
<attribute>
<srcPos sline="0" eline="0" spos="0" epos="0"/>
<jmpPos sline="0" eline="0" spos="0" epos="0"/>
<text info="Signature: Lorg/apache/flink/shaded/guava18/com/google/common/collect/Maps$EntrySet<TK;Ljava/util/Collection<TV;>;>;" aType="SignatureTag"/>
<text info="Enclosing Class: org/apache/flink/shaded/guava18/com/google/common/collect/FilteredEntryMultimap$AsMap Enclosing Method: createEntrySet Sig: ()Ljava/util/Set;" aType="EnclosingMethodTag"/>
<text info="[inner=org/apache/flink/shaded/guava18/com/google/common/collect/FilteredEntryMultimap$AsMap, outer=org/apache/flink/shaded/guava18/com/google/common/collect/FilteredEntryMultimap, name=AsMap,flags=0]" aType="InnerClassTag"/>
<text info="[inner=org/apache/flink/shaded/guava18/com/google/common/collect/FilteredEntryMultimap$AsMap$2, outer=null, name=null,flags=0]" aType="InnerClassTag"/>
<text info="[inner=org/apache/flink/shaded/guava18/com/google/common/collect/FilteredEntryMultimap$AsMap$2$1, outer=null, name=null,flags=0]" aType="InnerClassTag"/>
<text info="[inner=java/util/Map$Entry, outer=java/util/Map, name=Entry,flags=1545]" aType="InnerClassTag"/>
<text info="[inner=org/apache/flink/shaded/guava18/com/google/common/collect/Maps$EntrySet, outer=org/apache/flink/shaded/guava18/com/google/common/collect/Maps, name=EntrySet,flags=1032]" aType="InnerClassTag"/>
<text info="soot.tagkit.InnerClassAttribute@144c9aca" aType="InnerClassAttribute"/>
</attribute>
<attribute>
<srcPos sline="0" eline="0" spos="0" epos="0"/>
<jmpPos sline="21" eline="21" spos="0" epos="0"/>
<text info="Signature: ()Ljava/util/Map<TK;Ljava/util/Collection<TV;>;>;" aType="SignatureTag"/>
</attribute>
<attribute>
<srcPos sline="0" eline="0" spos="0" epos="0"/>
<jmpPos sline="33" eline="33" spos="0" epos="0"/>
<text info="Signature: ()Ljava/util/Iterator<Ljava/util/Map$Entry<TK;Ljava/util/Collection<TV;>;>;>;" aType="SignatureTag"/>
</attribute>
<attribute>
<srcPos sline="0" eline="0" spos="0" epos="0"/>
<jmpPos sline="47" eline="47" spos="0" epos="0"/>
<text info="Signature: (Ljava/util/Collection<*>;)Z" aType="SignatureTag"/>
</attribute>
<attribute>
<srcPos sline="0" eline="0" spos="0" epos="0"/>
<jmpPos sline="71" eline="71" spos="0" epos="0"/>
<text info="Signature: (Ljava/util/Collection<*>;)Z" aType="SignatureTag"/>
</attribute>
</attributes>
