<?xml version="1.0" encoding="ISO-8859-1"?>
<attributes>
<attribute>
<srcPos sline="0" eline="0" spos="0" epos="0"/>
<jmpPos sline="0" eline="0" spos="0" epos="0"/>
<text info="Signature: Lorg/apache/flink/shaded/guava18/com/google/common/collect/ForwardingCollection<Ljava/util/Map$Entry<TK;TV;>;>;" aType="SignatureTag"/>
<text info="[inner=org/apache/flink/shaded/guava18/com/google/common/collect/FilteredKeyMultimap$Entries, outer=org/apache/flink/shaded/guava18/com/google/common/collect/FilteredKeyMultimap, name=Entries,flags=0]" aType="InnerClassTag"/>
<text info="[inner=java/util/Map$Entry, outer=java/util/Map, name=Entry,flags=1545]" aType="InnerClassTag"/>
<text info="soot.tagkit.InnerClassAttribute@316d2bda" aType="InnerClassAttribute"/>
</attribute>
<attribute>
<srcPos sline="0" eline="0" spos="0" epos="0"/>
<jmpPos sline="21" eline="21" spos="0" epos="0"/>
<text info="Signature: ()Ljava/util/Collection<Ljava/util/Map$Entry<TK;TV;>;>;" aType="SignatureTag"/>
</attribute>
<attribute>
<srcPos sline="0" eline="0" spos="0" epos="0"/>
<jmpPos sline="46" eline="46" spos="0" epos="0"/>
<text info="Visibility Param Annotation: num params: 1 kind: 0
Visibility Annotation: level: RUNTIME (runtime-visible)
 Annotations:
Annotation type: Ljavax/annotation/Nullable; without elements

" aType="VisibilityParameterAnnotationTag"/>
</attribute>
</attributes>
