<?xml version="1.0" encoding="ISO-8859-1"?>
<attributes>
<attribute>
<srcPos sline="0" eline="0" spos="0" epos="0"/>
<jmpPos sline="0" eline="0" spos="0" epos="0"/>
<text info="[inner=org/apache/flink/util/InstantiationUtilTest$1, outer=null, name=null,flags=4104]" aType="InnerClassTag"/>
<text info="[inner=org/apache/flink/util/InstantiationUtilTest$WritableType, outer=org/apache/flink/util/InstantiationUtilTest, name=WritableType,flags=25]" aType="InnerClassTag"/>
<text info="[inner=org/apache/flink/util/InstantiationUtilTest$TestClassReadFailsCNF, outer=org/apache/flink/util/InstantiationUtilTest, name=TestClassReadFailsCNF,flags=10]" aType="InnerClassTag"/>
<text info="[inner=org/apache/flink/util/InstantiationUtilTest$TestClassReadFails, outer=org/apache/flink/util/InstantiationUtilTest, name=TestClassReadFails,flags=10]" aType="InnerClassTag"/>
<text info="[inner=org/apache/flink/util/InstantiationUtilTest$TestClassWriteFails, outer=org/apache/flink/util/InstantiationUtilTest, name=TestClassWriteFails,flags=10]" aType="InnerClassTag"/>
<text info="[inner=org/apache/flink/util/InstantiationUtilTest$TestException, outer=org/apache/flink/util/InstantiationUtilTest, name=TestException,flags=10]" aType="InnerClassTag"/>
<text info="[inner=org/apache/flink/util/InstantiationUtilTest$TestClass, outer=org/apache/flink/util/InstantiationUtilTest, name=TestClass,flags=2]" aType="InnerClassTag"/>
<text info="[inner=org/apache/flink/testutils/ClassLoaderUtils$ClassLoaderBuilder, outer=org/apache/flink/testutils/ClassLoaderUtils, name=ClassLoaderBuilder,flags=9]" aType="InnerClassTag"/>
<text info="soot.tagkit.InnerClassAttribute@fe9ddb5" aType="InnerClassAttribute"/>
</attribute>
<attribute>
<srcPos sline="0" eline="0" spos="0" epos="0"/>
<jmpPos sline="3" eline="3" spos="0" epos="0"/>
<text info="Visibility Annotation: level: RUNTIME (runtime-visible)
 Annotations:
Annotation type: Lorg/junit/ClassRule; without elements
" aType="VisibilityAnnotationTag"/>
</attribute>
<attribute>
<srcPos sline="0" eline="0" spos="0" epos="0"/>
<jmpPos sline="4" eline="4" spos="0" epos="0"/>
<text info="ConstantValue: import java.lang.reflect.InvocationHandler;import java.lang.reflect.Method;import java.io.Serializable;public class %s implements InvocationHandler, Serializable {

  @Override
  public Object invoke(Object proxy, Method method, Object[] args) throws Throwable {
    return null;
  }
}" aType="StringConstantValueTag"/>
</attribute>
<attribute>
<srcPos sline="0" eline="0" spos="0" epos="0"/>
<jmpPos sline="17" eline="17" spos="0" epos="0"/>
<text info="Visibility Annotation: level: RUNTIME (runtime-visible)
 Annotations:
Annotation type: Lorg/junit/Test; without elements
" aType="VisibilityAnnotationTag"/>
</attribute>
<attribute>
<srcPos sline="0" eline="0" spos="0" epos="0"/>
<jmpPos sline="165" eline="165" spos="0" epos="0"/>
<text info="Visibility Annotation: level: RUNTIME (runtime-visible)
 Annotations:
Annotation type: Lorg/junit/Test; without elements
" aType="VisibilityAnnotationTag"/>
</attribute>
<attribute>
<srcPos sline="0" eline="0" spos="0" epos="0"/>
<jmpPos sline="182" eline="182" spos="0" epos="0"/>
<text info="Visibility Annotation: level: RUNTIME (runtime-visible)
 Annotations:
Annotation type: Lorg/junit/Test; without elements
" aType="VisibilityAnnotationTag"/>
</attribute>
<attribute>
<srcPos sline="0" eline="0" spos="0" epos="0"/>
<jmpPos sline="199" eline="199" spos="0" epos="0"/>
<text info="Visibility Annotation: level: RUNTIME (runtime-visible)
 Annotations:
Annotation type: Lorg/junit/Test; without elements
" aType="VisibilityAnnotationTag"/>
</attribute>
<attribute>
<srcPos sline="0" eline="0" spos="0" epos="0"/>
<jmpPos sline="213" eline="213" spos="0" epos="0"/>
<text info="Visibility Annotation: level: RUNTIME (runtime-visible)
 Annotations:
Annotation type: Lorg/junit/Test; without elements
" aType="VisibilityAnnotationTag"/>
</attribute>
<attribute>
<srcPos sline="0" eline="0" spos="0" epos="0"/>
<jmpPos sline="227" eline="227" spos="0" epos="0"/>
<text info="Visibility Annotation: level: RUNTIME (runtime-visible)
 Annotations:
Annotation type: Lorg/junit/Test; without elements
" aType="VisibilityAnnotationTag"/>
</attribute>
<attribute>
<srcPos sline="0" eline="0" spos="0" epos="0"/>
<jmpPos sline="241" eline="241" spos="0" epos="0"/>
<text info="Visibility Annotation: level: RUNTIME (runtime-visible)
 Annotations:
Annotation: type: Lorg/junit/Test; num elems: 1 elems: 
Annotation Element: kind: c name: expected decription: Ljava/lang/RuntimeException;

" aType="VisibilityAnnotationTag"/>
</attribute>
<attribute>
<srcPos sline="0" eline="0" spos="0" epos="0"/>
<jmpPos sline="252" eline="252" spos="0" epos="0"/>
<text info="Visibility Annotation: level: RUNTIME (runtime-visible)
 Annotations:
Annotation type: Lorg/junit/Test; without elements
" aType="VisibilityAnnotationTag"/>
</attribute>
<attribute>
<srcPos sline="0" eline="0" spos="0" epos="0"/>
<jmpPos sline="284" eline="284" spos="0" epos="0"/>
<text info="Visibility Annotation: level: RUNTIME (runtime-visible)
 Annotations:
Annotation type: Lorg/junit/Test; without elements
" aType="VisibilityAnnotationTag"/>
</attribute>
<attribute>
<srcPos sline="0" eline="0" spos="0" epos="0"/>
<jmpPos sline="408" eline="408" spos="0" epos="0"/>
<text info="Visibility Annotation: level: RUNTIME (runtime-visible)
 Annotations:
Annotation type: Lorg/junit/Test; without elements
" aType="VisibilityAnnotationTag"/>
</attribute>
</attributes>
